{"namedChunkGroups":{"polyfill":{"name":"polyfill","assets":[{"name":"webpack-runtime-95cf1a6994de8e70cfc8.js","size":4899},{"name":"polyfill-a3d41b2066b5d1d4cd76.js","size":82629}],"filteredAssets":0,"assetsSize":87528,"filteredAuxiliaryAssets":2,"auxiliaryAssetsSize":221010},"app":{"name":"app","assets":[{"name":"webpack-runtime-95cf1a6994de8e70cfc8.js","size":4899},{"name":"framework-5a85c39ef4c6f793683b.js","size":128957},{"name":"app-1a4b540377749e319015.js","size":126450}],"filteredAssets":0,"assetsSize":260306,"filteredAuxiliaryAssets":3,"auxiliaryAssetsSize":839704},"component---src-pages-404-js":{"name":"component---src-pages-404-js","assets":[{"name":"component---src-pages-404-js-b13c7e2af936e0d77284.js","size":808}],"filteredAssets":0,"assetsSize":808,"filteredAuxiliaryAssets":1,"auxiliaryAssetsSize":1883},"component---src-pages-index-js":{"name":"component---src-pages-index-js","assets":[{"name":"styles.1a1855db725a9815ee92.css","size":8186},{"name":"a9a7754c-7957454080189e398156.js","size":5870},{"name":"component---src-pages-index-js-cc2d624979454f46e60b.js","size":45915}],"filteredAssets":0,"assetsSize":59971,"filteredAuxiliaryAssets":5,"auxiliaryAssetsSize":14123131}},"assetsByChunkName":{"polyfill":["webpack-runtime-95cf1a6994de8e70cfc8.js","polyfill-a3d41b2066b5d1d4cd76.js"],"app":["webpack-runtime-95cf1a6994de8e70cfc8.js","framework-5a85c39ef4c6f793683b.js","app-1a4b540377749e319015.js"],"component---src-pages-404-js":["component---src-pages-404-js-b13c7e2af936e0d77284.js"],"component---src-pages-index-js":["styles.1a1855db725a9815ee92.css","a9a7754c-7957454080189e398156.js","component---src-pages-index-js-cc2d624979454f46e60b.js"]},"childAssetsByChunkName":{}}